llm_samba/__init__.py
llm_samba/llm_samba.py
llm_samba-0.1.1.dist-info/licenses/LICENSE
llm_samba-0.1.1.dist-info/METADATA
llm_samba-0.1.1.dist-info/WHEEL
llm_samba-0.1.1.dist-info/entry_points.txt
llm_samba-0.1.1.dist-info/top_level.txt
llm_samba-0.1.1.dist-info/RECORD
