Metadata-Version: 2.4
Name: llm-samba
Version: 0.1.1
Summary: LLM plugin providing access to the free Samba models using the samba API
Author: Samuel Dantas
License: Apache-2.0
Project-URL: Homepage, https://github.com/Tatarotus/llm-samba
Project-URL: Changelog, https://github.com/Tatarotus/llm-samba/releases
Project-URL: Issues, https://github.com/Tatarotus/llm-samba/issues
Project-URL: CI, https://github.com/Tatarotus/llm-samba/actions
Classifier: License :: OSI Approved :: Apache Software License
License-File: LICENSE
Requires-Dist: llm>=0.17
Requires-Dist: httpx
Requires-Dist: httpx-sse
Provides-Extra: test
Requires-Dist: pytest; extra == "test"
Requires-Dist: pytest-httpx; extra == "test"
Dynamic: license-file
